plotszoo/__init__.py
plotszoo/utils.py
plotszoo/data/__init__.py
plotszoo/data/datacollection.py
plotszoo/data/optunadata.py
plotszoo/data/wandbdata.py
plotszoo/scalars/__init__.py
plotszoo/scalars/parallel.py
plotszoo/scalars/scalarsplot.py
plotszoo/scalars/scattercumulative.py
plotszoo/scalars/grouped/__init__.py
plotszoo/scalars/grouped/barchart.py
plotszoo/series/__init__.py
plotszoo/series/parade.py
plotszoo/series/seriesplot.py
plotszoo/series/grouped/__init__.py
plotszoo/series/grouped/parade.py
plotszoo-0.1.dist-info/LICENSE
plotszoo-0.1.dist-info/METADATA
plotszoo-0.1.dist-info/WHEEL
plotszoo-0.1.dist-info/top_level.txt
plotszoo-0.1.dist-info/RECORD
