Metadata-Version: 2.1
Name: plotszoo
Version: 0.1
Summary: Collection of utilities to make plots
Home-page: https://github.com/galatolofederico/plotszoo
Author: Federico A. Galatolo
Author-email: federico.galatolo@ing.unipi.it
License: UNKNOWN
Platform: UNKNOWN
Classifier: Programming Language :: Python :: 3.7
Classifier: License :: OSI Approved :: GNU General Public License v3 (GPLv3)
Classifier: Operating System :: OS Independent
Classifier: Topic :: Scientific/Engineering :: Visualization
Classifier: Intended Audience :: Science/Research
Classifier: Development Status :: 4 - Beta
License-File: LICENSE
Requires-Dist: numpy (==1.19.4)
Requires-Dist: pandas (==1.1.4)
Requires-Dist: scipy (==1.5.4)
Requires-Dist: matplotlib (==3.3.2)
